exponentation/__init__.py
exponentation/methods.py
exponentation/neuron.py
exponentation/settings.py
exponentation/utils.py
exponentation/data/Data_learning.csv
exponentation/data/my_model.pth
exponentation-1.0.0.dist-info/METADATA
exponentation-1.0.0.dist-info/WHEEL
exponentation-1.0.0.dist-info/top_level.txt
exponentation-1.0.0.dist-info/RECORD
