Metadata-Version: 2.1
Name: exponentation
Version: 1.0.0
Summary: This is a computational library based on AI for optimal exponentiation.
Home-page: https://github.com/Katyana01/Library.git
Author: katya_r
Author-email: katerina.riabova@gmail.com
Project-URL: GitHub, https://github.com/Katyana01/Library
Keywords: files speedfiles
Classifier: Programming Language :: Python :: 3.11
Classifier: License :: OSI Approved :: MIT License
Classifier: Operating System :: OS Independent
Requires-Python: >=3.9
Requires-Dist: pandas
Requires-Dist: torch
Requires-Dist: numpy
